.VERSION
AUTHORS.rst
CONTRIBUTING.rst
HISTORY.rst
LICENSE
MANIFEST.in
Pipfile
Pipfile.lock
README.rst
USAGE.rst
dev-requirements.txt
requirements.txt
setup.cfg
setup.py
audioaddictapilib/.VERSION
audioaddictapilib/AUTHORS.rst
audioaddictapilib/CONTRIBUTING.rst
audioaddictapilib/HISTORY.rst
audioaddictapilib/LICENSE
audioaddictapilib/Pipfile
audioaddictapilib/Pipfile.lock
audioaddictapilib/README.rst
audioaddictapilib/USAGE.rst
audioaddictapilib/__init__.py
audioaddictapilib/_version.py
audioaddictapilib/audioaddictapilib.py
audioaddictapilib/audioaddictapilibexceptions.py
audioaddictapilib/configuration.py
audioaddictapilib/dev-requirements.txt
audioaddictapilib/requirements.txt
audioaddictapilib.egg-info/PKG-INFO
audioaddictapilib.egg-info/SOURCES.txt
audioaddictapilib.egg-info/dependency_links.txt
audioaddictapilib.egg-info/not-zip-safe
audioaddictapilib.egg-info/requires.txt
audioaddictapilib.egg-info/top_level.txt
docs/Makefile
docs/authors.rst
docs/conf.py
docs/contributing.rst
docs/history.rst
docs/index.rst
docs/installation.rst
docs/readme.rst
docs/usage.rst
tests/test_audioaddictapilib.py