Metadata-Version: 2.1
Name: audioaddictapilib
Version: 0.1.0
Summary: Library to interact with the Audioaddict API
Home-page: https://github.com/jendab/audioaddictapilib
Author: Jenda Brands
Author-email: jenda@brnds.eu
License: MIT
Keywords: audioaddictapilib
Classifier: Development Status :: 2 - Pre-Alpha
Classifier: Intended Audience :: Developers
Classifier: License :: OSI Approved :: MIT License
Classifier: Natural Language :: English
Classifier: Programming Language :: Python :: 3.9
License-File: LICENSE
License-File: AUTHORS.rst
Requires-Dist: sonosaudioservicelib>=0.3.0
Requires-Dist: beautifulsoup4>=4.12.2; python_full_version >= "3.6.0"
Requires-Dist: pytz>=2023.3.post1
Requires-Dist: requests>=2.31.0; python_version >= "3.7"
